.gitignore
.travis.yml
CHANGES.rst
MANIFEST.in
README.rst
base.cfg
bootstrap.py
buildout.cfg
plone.cfg
setup.cfg
setup.py
travis-4.2.x.cfg
travis-4.3.x.cfg
docs/INSTALL.txt
docs/LICENSE.GPL
docs/LICENSE.txt
src/collective/__init__.py
src/collective.contentleadimage.egg-info/PKG-INFO
src/collective.contentleadimage.egg-info/SOURCES.txt
src/collective.contentleadimage.egg-info/dependency_links.txt
src/collective.contentleadimage.egg-info/entry_points.txt
src/collective.contentleadimage.egg-info/namespace_packages.txt
src/collective.contentleadimage.egg-info/not-zip-safe
src/collective.contentleadimage.egg-info/requires.txt
src/collective.contentleadimage.egg-info/top_level.txt
src/collective/contentleadimage/README.txt
src/collective/contentleadimage/TODO.txt
src/collective/contentleadimage/__init__.py
src/collective/contentleadimage/config.py
src/collective/contentleadimage/configure.zcml
src/collective/contentleadimage/extender.py
src/collective/contentleadimage/interfaces.py
src/collective/contentleadimage/leadimageprefs.py
src/collective/contentleadimage/migration.py
src/collective/contentleadimage/purgeurls.py
src/collective/contentleadimage/setuphandlers.py
src/collective/contentleadimage/testing.py
src/collective/contentleadimage/usei18ndude.sh
src/collective/contentleadimage/utils.py
src/collective/contentleadimage/vocabulary.py
src/collective/contentleadimage/Extensions/Install.py
src/collective/contentleadimage/browser/__init__.py
src/collective/contentleadimage/browser/configure.zcml
src/collective/contentleadimage/browser/contentleadimage.css
src/collective/contentleadimage/browser/folder_leadimage_view.pt
src/collective/contentleadimage/browser/folder_leadimage_view.py
src/collective/contentleadimage/browser/leadimage-body.pt
src/collective/contentleadimage/browser/leadimage.pt
src/collective/contentleadimage/browser/viewlets.py
src/collective/contentleadimage/locales/collective.contentleadimage.pot
src/collective/contentleadimage/locales/manual.pot
src/collective/contentleadimage/locales/cs/LC_MESSAGES/collective.contentleadimage.po
src/collective/contentleadimage/locales/de/LC_MESSAGES/collective.contentleadimage.po
src/collective/contentleadimage/locales/en/LC_MESSAGES/collective.contentleadimage.po
src/collective/contentleadimage/locales/es/LC_MESSAGES/collective.contentleadimage.po
src/collective/contentleadimage/locales/fr/LC_MESSAGES/collective.contentleadimage.po
