Metadata-Version: 2.1
Name: collective.contentleadimage
Version: 1.3.6
Summary: Adds lead image to any content in plone site
Home-page: http://pypi.python.org/pypi/collective.contentleadimage
Author: Radim Novotny
Author-email: novotny.radim@gmail.com
License: GPL
Keywords: plone
Platform: UNKNOWN
Classifier: Framework :: Plone
Classifier: Framework :: Zope2
Classifier: Framework :: Zope3
Classifier: Programming Language :: Python
Classifier: Topic :: Software Development :: Libraries :: Python Modules
Provides-Extra: test
